release_feed_mediola/__init__.py
release_feed_mediola/__main__.py
release_feed_mediola/api.py
release_feed_mediola/cli.py
release_feed_mediola/settings.py
release_feed_mediola-0.3.0.dist-info/LICENSE
release_feed_mediola-0.3.0.dist-info/METADATA
release_feed_mediola-0.3.0.dist-info/WHEEL
release_feed_mediola-0.3.0.dist-info/entry_points.txt
release_feed_mediola-0.3.0.dist-info/RECORD
