Metadata-Version: 2.1
Name: release_feed_mediola
Version: 0.3.0
Summary: Atom feed for software product releases of Mediola AG
License: Apache-2.0
Author: Claudia Pellegrino
Author-email: clau@tiqua.de
Requires-Python: >=3.12
Classifier: License :: OSI Approved :: Apache Software License
Classifier: Programming Language :: Python :: 3
Classifier: Programming Language :: Python :: 3.12
Requires-Dist: feedgen (>=1.0,<2.0)
Requires-Dist: requests (>=2.32.0,<3.0.0)
